CycLog/CycleLog.py
CycLog/__init__.py
CycLog/utils.py
CycLog-1.1.2.dist-info/METADATA
CycLog-1.1.2.dist-info/WHEEL
CycLog-1.1.2.dist-info/top_level.txt
CycLog-1.1.2.dist-info/RECORD
