Metadata-Version: 2.1
Name: CycLog
Version: 1.1.2
Summary: A python module to handle cyclic logs.
Home-page: https://github.com/jonatan1609/CycleLog
Author: Jonatan
Author-email: pybots.il@gmail.com
License: UNKNOWN
Platform: UNKNOWN
Classifier: License :: OSI Approved :: The Unlicense (Unlicense)
Classifier: Programming Language :: Python :: 3
Classifier: Operating System :: OS Independent
Classifier: Topic :: System :: Logging
Requires-Python: >=3
